poottu/__init__.py
poottu/main.py
poottu/core/__init__.py
poottu/core/database.py
poottu/core/encryption.py
poottu/core/vault.py
poottu/gui/__init__.py
poottu/gui/create_window.py
poottu/gui/dialogs.py
poottu/gui/main_window.py
poottu/gui/unlock_window.py
poottu/resources/icon.ico
poottu/resources/icon.png
poottu/utils/__init__.py
poottu/utils/backup.py
poottu/utils/paths.py
poottu-1.0.1.dist-info/licenses/LICENSE
poottu-1.0.1.dist-info/licenses/LICENSE.txt
poottu-1.0.1.dist-info/METADATA
poottu-1.0.1.dist-info/WHEEL
poottu-1.0.1.dist-info/entry_points.txt
poottu-1.0.1.dist-info/top_level.txt
poottu-1.0.1.dist-info/RECORD
