Metadata-Version: 2.4
Name: poottu
Version: 1.0.1
Summary: Poottu Password Manager
Author-email: Manikandan D <manikandan@due.im>
License: MIT License
Project-URL: Homepage, https://due.im/poottu/
Project-URL: Repository, https://github.com/manikandancode/poottu
Project-URL: BugTracker, https://github.com/manikandancode/poottu/issues
Keywords: password-manager,offline-password-manager,password,secure-password-generator,python-password-manager,password-manager-app
Classifier: Development Status :: 5 - Production/Stable
Classifier: Intended Audience :: End Users/Desktop
Classifier: License :: OSI Approved :: MIT License
Classifier: Programming Language :: Python :: 3
Classifier: Programming Language :: Python :: 3.12
Classifier: Programming Language :: Python :: 3.13
Classifier: Operating System :: OS Independent
Classifier: Topic :: Utilities
Classifier: Topic :: Security
Classifier: Topic :: Security :: Cryptography
Requires-Python: <3.14,>=3.12
License-File: LICENSE
License-File: LICENSE.txt
Requires-Dist: PySide6>=6.5.0
Requires-Dist: argon2-cffi>=21.3.0
Requires-Dist: pynacl>=1.5.0
Requires-Dist: zxcvbn>=4.5.0
Requires-Dist: cryptography>=41.0.0
Requires-Dist: platformdirs>=3.0.0
Dynamic: license-file
